odoo/addons/l10n_fr_account_vat_return/README.rst
odoo/addons/l10n_fr_account_vat_return/__init__.py
odoo/addons/l10n_fr_account_vat_return/__manifest__.py
odoo/addons/l10n_fr_account_vat_return/post_install.py
odoo/addons/l10n_fr_account_vat_return/data/account_fiscal_position_template.xml
odoo/addons/l10n_fr_account_vat_return/data/l10n.fr.account.vat.box.csv
odoo/addons/l10n_fr_account_vat_return/i18n/fr.po
odoo/addons/l10n_fr_account_vat_return/i18n/l10n_fr_account_vat_return.pot
odoo/addons/l10n_fr_account_vat_return/migrations/0.0.0/pre-migration.py
odoo/addons/l10n_fr_account_vat_return/migrations/14.0.2.0.0/post-migrate.py
odoo/addons/l10n_fr_account_vat_return/migrations/14.0.2.0.0/pre-migrate.py
odoo/addons/l10n_fr_account_vat_return/migrations/14.0.5.0.0/pre-migrate.py
odoo/addons/l10n_fr_account_vat_return/migrations/14.0.6.1.1/pre-migrate.py
odoo/addons/l10n_fr_account_vat_return/migrations/14.0.8.0.0/post-migration.py
odoo/addons/l10n_fr_account_vat_return/models/__init__.py
odoo/addons/l10n_fr_account_vat_return/models/account_account.py
odoo/addons/l10n_fr_account_vat_return/models/account_fiscal_position.py
odoo/addons/l10n_fr_account_vat_return/models/account_move.py
odoo/addons/l10n_fr_account_vat_return/models/account_move_line.py
odoo/addons/l10n_fr_account_vat_return/models/account_partial_reconcile.py
odoo/addons/l10n_fr_account_vat_return/models/account_tax.py
odoo/addons/l10n_fr_account_vat_return/models/l10n_fr_account_vat_box.py
odoo/addons/l10n_fr_account_vat_return/models/l10n_fr_account_vat_return.py
odoo/addons/l10n_fr_account_vat_return/models/res_company.py
odoo/addons/l10n_fr_account_vat_return/readme/CONTRIBUTORS.rst
odoo/addons/l10n_fr_account_vat_return/readme/DESCRIPTION.rst
odoo/addons/l10n_fr_account_vat_return/report/CA3_cerfa.pdf
odoo/addons/l10n_fr_account_vat_return/security/ir.model.access.csv
odoo/addons/l10n_fr_account_vat_return/security/ir_rule.xml
odoo/addons/l10n_fr_account_vat_return/static/description/icon.png
odoo14_addon_l10n_fr_account_vat_return-14.0.9.0.0.dist-info/METADATA
odoo14_addon_l10n_fr_account_vat_return-14.0.9.0.0.dist-info/WHEEL
odoo14_addon_l10n_fr_account_vat_return-14.0.9.0.0.dist-info/top_level.txt
odoo14_addon_l10n_fr_account_vat_return-14.0.9.0.0.dist-info/RECORD
