Metadata-Version: 2.1
Name: odoo14-addon-l10n_fr_account_vat_return
Version: 14.0.9.0.0
Summary: VAT return for France: CA3, 3310-A, 3519
Home-page: https://github.com/OCA/l10n-france
Author: Akretion,Odoo Community Association (OCA)
Author-email: support@odoo-community.org
License: AGPL-3
Classifier: Programming Language :: Python
Classifier: Framework :: Odoo
Classifier: Framework :: Odoo :: 14.0
Classifier: License :: OSI Approved :: GNU Affero General Public License v3
Requires-Python: >=3.6
Requires-Dist: odoo14-addon-intrastat-base
Requires-Dist: odoo14-addon-l10n-fr-oca
Requires-Dist: odoo14-addon-onchange-helper
Requires-Dist: odoo<14.1dev,>=14.0a
Requires-Dist: pypdf>=3.1.0
